nexedge/__init__.py
nexedge/__version__.py
nexedge/channel.py
nexedge/communicator.py
nexedge/compressor.py
nexedge/encoder.py
nexedge/exceptions.py
nexedge/packer.py
nexedge/pcip_commands.py
nexedge/radio.py
nexedge/utils.py
nexedge-1.0.0.dist-info/LICENSE.md
nexedge-1.0.0.dist-info/METADATA
nexedge-1.0.0.dist-info/WHEEL
nexedge-1.0.0.dist-info/top_level.txt
nexedge-1.0.0.dist-info/RECORD
