Metadata-Version: 2.1
Name: nexedge
Version: 1.0.0
Summary: Kenwood Nexedge communication
Home-page: https://github.com/evocount/nexedge
Author: Suthep Pomjaksilp
Author-email: sp@laz0r.de
License: MIT
Platform: UNKNOWN
Classifier: Development Status :: 5 - Production/Stable
Classifier: Intended Audience :: Developers
Classifier: License :: OSI Approved :: MIT License
Classifier: Programming Language :: Python
Classifier: Programming Language :: Python :: 3
Classifier: Programming Language :: Python :: 3.6
Classifier: Programming Language :: Python :: Implementation :: CPython
Classifier: Programming Language :: Python :: Implementation :: PyPy
Classifier: Topic :: Communications
Requires-Python: >=3.6.0
Requires-Dist: pyserial-asyncio
Provides-Extra: test
Requires-Dist: pytest ; extra == 'test'
Requires-Dist: pytest-cov ; extra == 'test'
Requires-Dist: pytest-asyncio ; extra == 'test'
Requires-Dist: pytest-mock ; extra == 'test'
Requires-Dist: pytest-xdist ; extra == 'test'
